{"format":2,"version":"7.3.2","globals":"5240877b548903939ea6d4ec8152870e","files":{"d_cf39f571bb422ee7___init___py":{"hash":"e6baa73cda2916dad605215f937a92e1","index":{"nums":[0,1,0,0,0,0,0,0],"html_filename":"d_cf39f571bb422ee7___init___py.html","relative_filename":"src/extratools_gittools/__init__.py"}},"d_cf39f571bb422ee7_prompt_py":{"hash":"19bb54771756cba914507bd43c48dc8b","index":{"nums":[0,1,41,0,41,0,0,0],"html_filename":"d_cf39f571bb422ee7_prompt_py.html","relative_filename":"src/extratools_gittools/prompt.py"}},"d_cf39f571bb422ee7_repo_py":{"hash":"beff4c3f2fb64d9b295622b959b5222d","index":{"nums":[0,1,79,0,79,0,0,0],"html_filename":"d_cf39f571bb422ee7_repo_py.html","relative_filename":"src/extratools_gittools/repo.py"}},"d_cf39f571bb422ee7_status_py":{"hash":"23bb18388619a4f03cbb3feca749475a","index":{"nums":[0,1,50,0,7,0,0,0],"html_filename":"d_cf39f571bb422ee7_status_py.html","relative_filename":"src/extratools_gittools/status.py"}}}}